omc_scanalyzer
