Metadata-Version: 1.0
Name: omc-scanalyzer
Version: 0.2.5
Summary: A tool developed for analyzing OMC scans at LIGO
Home-page: UNKNOWN
Author: Alexei Ciobanu
Author-email: alexei.ciobanu95@gmail.com
License: UNKNOWN
Platform: UNKNOWN
